LICENSE
MANIFEST.in
README.rst
requirements-test.in
requirements-test.txt
requirements.in
requirements.txt
setup.cfg
setup.py
h1/__init__.py
h1/client.py
h1/lazy_listing.py
h1/models.py
h1.egg-info/PKG-INFO
h1.egg-info/SOURCES.txt
h1.egg-info/dependency_links.txt
h1.egg-info/not-zip-safe
h1.egg-info/requires.txt
h1.egg-info/top_level.txt
tests/__init__.py
tests/test_client.py
tests/test_lazy_listing.py
tests/test_models.py
tests/resources/activity-agreed-on-going-public.json
tests/resources/activity-bounty-awarded.json
tests/resources/activity-bounty-suggested.json
tests/resources/activity-bug-cloned.json
tests/resources/activity-bug-duplicate.json
tests/resources/activity-bug-informative.json
tests/resources/activity-bug-needs-more-info.json
tests/resources/activity-bug-new.json
tests/resources/activity-bug-not-applicable.json
tests/resources/activity-bug-reopened.json
tests/resources/activity-bug-resolved.json
tests/resources/activity-bug-spam.json
tests/resources/activity-bug-triaged.json
tests/resources/activity-comment.json
tests/resources/activity-comments-closed.json
tests/resources/activity-external-user-invitation-cancelled.json
tests/resources/activity-external-user-invited.json
tests/resources/activity-external-user-joined.json
tests/resources/activity-external-user-removed.json
tests/resources/activity-group-assigned-to-bug.json
tests/resources/activity-hacker-requested-mediation.json
tests/resources/activity-manually-disclosed.json
tests/resources/activity-mediation-requested.json
tests/resources/activity-not-eligible-for-bounty.json
tests/resources/activity-reference-id-added.json
tests/resources/activity-report-became-public.json
tests/resources/activity-report-severity-updated.json
tests/resources/activity-report-title-updated.json
tests/resources/activity-report-vulnerability-types-updated.json
tests/resources/activity-swag-awarded.json
tests/resources/activity-user-assigned-to-bug.json
tests/resources/activity-user-banned-from-program.json
tests/resources/address.json
tests/resources/attachment.json
tests/resources/bounty.json
tests/resources/group.json
tests/resources/program.json
