Metadata-Version: 1.1
Name: h1
Version: 1.4.1
Summary: A HackerOne API client for Python
Home-page: https://github.com/uber-common/h1-python
Author: Uber Product Security
Author-email: UNKNOWN
License: MIT
Platform: UNKNOWN
Classifier: Topic :: Internet :: WWW/HTTP
Classifier: Topic :: Software Development :: Libraries
Classifier: Programming Language :: Python :: 2.7
Classifier: Programming Language :: Python :: 3
